[{"senderKeyId":592319912,"senderChainKey":{"iteration":204,"seed":"r47Ddp3CymOtkUqmG4EMdYcZDDcMxOoyYxx8mY82x5g="},"senderSigningKey":{"public":"BeC7wXvyKiwV3bslcTSQoopPk8pxZVWfG4DkxVnTlT8H"},"senderMessageKeys":[{},{},{},{},{},{},{},{},{},{},{},{},{},{},{},{},{},{},{},{},{},{},{},{},{},{},{},{},{},{},{},{},{},{},{},{},{},{},{},{},{},{},{},{},{},{},{},{},{},{},{},{},{},{},{},{},{},{},{},{},{},{},{},{},{},{},{},{},{},{},{},{},{},{},{},{},{},{},{},{},{},{},{},{},{},{},{},{},{},{},{},{},{},{},{},{},{},{},{},{},{},{},{},{},{},{},{},{},{},{},{},{},{},{},{},{},{},{},{},{}]}]]}]